README.txt
setup.cfg
setup.py
docs/HISTORY.txt
docs/INSTALL.txt
docs/LICENSE.GPL
docs/LICENSE.txt
medialog/__init__.py
medialog.moreviews.egg-info/PKG-INFO
medialog.moreviews.egg-info/SOURCES.txt
medialog.moreviews.egg-info/dependency_links.txt
medialog.moreviews.egg-info/entry_points.txt
medialog.moreviews.egg-info/namespace_packages.txt
medialog.moreviews.egg-info/not-zip-safe
medialog.moreviews.egg-info/paster_plugins.txt
medialog.moreviews.egg-info/requires.txt
medialog.moreviews.egg-info/top_level.txt
medialog/moreviews/__init__.py
medialog/moreviews/configure.zcml
medialog/moreviews/tests.py
medialog/moreviews/browser/__init__.py
medialog/moreviews/browser/colorizedimageview.py
medialog/moreviews/browser/configure.zcml
medialog/moreviews/browser/dropshadowimageview.py
medialog/moreviews/browser/imageviews.py
medialog/moreviews/browser/mytestview.py
medialog/moreviews/browser/placepage-turner.pt
medialog/moreviews/browser/slidercollection.pt
medialog/moreviews/browser/truegallerycollection.pt
medialog/moreviews/browser/views.py
medialog/moreviews/profiles/default/cssregistry.xml
medialog/moreviews/profiles/default/jsregistry.xml
medialog/moreviews/profiles/default/metadata.xml
medialog/moreviews/profiles/default/propertiestool.xml
medialog/moreviews/profiles/default/skins.xml
medialog/moreviews/profiles/default/types.xml
medialog/moreviews/profiles/default/types/Folder.xml
medialog/moreviews/profiles/default/types/Image.xml
medialog/moreviews/profiles/default/types/News_Item.xml
medialog/moreviews/profiles/default/types/Topic.xml
medialog/moreviews/profiles/newsitemviews/metadata.xml
medialog/moreviews/profiles/newsitemviews/propertiestool.xml
medialog/moreviews/profiles/newsitemviews/skins.xml
medialog/moreviews/profiles/newsitemviews/types.xml
medialog/moreviews/profiles/newsitemviews/types/News_Item.xml
medialog/moreviews/profiles/visualbox2/cssregistry.xml
medialog/moreviews/profiles/visualbox2/jsregistry.xml
medialog/moreviews/profiles/visualbox2/metadata.xml
medialog/moreviews/profiles/visualbox2/propertiestool.xml
medialog/moreviews/profiles/visualbox2/skins.xml
medialog/moreviews/profiles/visualbox2/types.xml
medialog/moreviews/profiles/visualbox2/types/Folder.xml
medialog/moreviews/profiles/visualbox2/types/Topic.xml
medialog/moreviews/skins/moreviews/bigger_news_item.pt
medialog/moreviews/skins/moreviews/bigger_news_item.pt.metadata
