Metadata-Version: 1.0
Name: medialog.moreviews
Version: 0.8.3
Summary: More views for plone 4 (ONLY).
Home-page: http://svn.plone.org/svn/collective/
Author: UNKNOWN
Author-email: UNKNOWN
License: GPL
Platform: UNKNOWN
Classifier: Framework :: Plone
Classifier: Programming Language :: Python
